Pythonlqc-0.0.123.data/data/cut_video/to_erase.json
Pythonlqc-0.0.123.data/scripts/cut_video.py
cut_video/__init__.py
cut_video/cut_video.py
Pythonlqc-0.0.123.dist-info/LICENCE
Pythonlqc-0.0.123.dist-info/METADATA
Pythonlqc-0.0.123.dist-info/WHEEL
Pythonlqc-0.0.123.dist-info/entry_points.txt
Pythonlqc-0.0.123.dist-info/top_level.txt
Pythonlqc-0.0.123.dist-info/RECORD
